militarynlp/__init__.py
militarynlp/special_military_operations.py
militarynlp-0.0.3.dist-info/LICENSE
militarynlp-0.0.3.dist-info/METADATA
militarynlp-0.0.3.dist-info/WHEEL
militarynlp-0.0.3.dist-info/top_level.txt
militarynlp-0.0.3.dist-info/RECORD
