Metadata-Version: 2.1
Name: militarynlp
Version: 0.0.3
Summary: Narrating Military Using Python.
Home-page: https://cpanlp.com
Author: Draco Deng
Author-email: dracodeng6@gmail.com
License: MIT
Keywords: python,military,intelligent military,linguistic turn,linguistic
Classifier: Intended Audience :: Developers
Classifier: License :: OSI Approved :: MIT License
Classifier: Programming Language :: Python :: 3
Classifier: Operating System :: Unix
Classifier: Operating System :: MacOS :: MacOS X
Classifier: Operating System :: Microsoft :: Windows
Classifier: Natural Language :: English
Classifier: Natural Language :: Chinese (Simplified)
License-File: LICENSE
